MANIFEST.in
README.md
setup.cfg
setup.py
exogas/__init__.py
exogas/constants.py
exogas/functions_misc.py
exogas/radial_simulation.py
exogas/vertical_simulation.py
exogas.egg-info/PKG-INFO
exogas.egg-info/SOURCES.txt
exogas.egg-info/dependency_links.txt
exogas.egg-info/requires.txt
exogas.egg-info/top_level.txt
exogas/photodissociation/Sigma_C1_Mearth_au2.txt
exogas/photodissociation/Sigma_CO_Mearth_au2.txt
exogas/photodissociation/self-shielding.dat
exogas/photodissociation/tau_CO_yr_layered.txt
exogas/photodissociation/tau_CO_yr_mixed.txt